fits_utilities/__init__.py
fits_utilities/hselect.py
fits_utilities/imhead.py
fits_utilities/showfits.py
fits_utilities/update_keywords.py
fits_utilities/upload_files_to_zenodo.py
fits_utilities/version.py
tests/__init__.py
tests/test_imports.py
fits_utilities-0.1.2.dist-info/LICENSE
fits_utilities-0.1.2.dist-info/METADATA
fits_utilities-0.1.2.dist-info/WHEEL
fits_utilities-0.1.2.dist-info/entry_points.txt
fits_utilities-0.1.2.dist-info/top_level.txt
fits_utilities-0.1.2.dist-info/RECORD
