Metadata-Version: 2.1
Name: fits-utilities
Version: 0.1.2
Summary: Tools for visualizing fits files.
Home-page: https://github.com/simontorres/fits_utilities
Author: Simon Torres R., 
Author-email: storres@ctio.noao.edu
License: BSD-3-Clause
Keywords: astronomy images
Platform: UNKNOWN
Classifier: Development Status :: 5 - Production/Stable
Classifier: Environment :: Console
Classifier: Intended Audience :: Developers
Classifier: Intended Audience :: Education
Classifier: Intended Audience :: Science/Research
Classifier: License :: OSI Approved :: BSD License
Classifier: Programming Language :: Python :: 3.6
Classifier: Programming Language :: Python :: 3.8
Classifier: Natural Language :: English
Classifier: Operating System :: POSIX :: Linux
Classifier: Operating System :: POSIX :: Other
Classifier: Operating System :: MacOS :: MacOS X
Classifier: Topic :: Scientific/Engineering :: Astronomy
Classifier: Topic :: Scientific/Engineering :: Information Analysis
Classifier: Topic :: Software Development :: Libraries :: Python Modules
Requires-Dist: numpy
Requires-Dist: pandas
Requires-Dist: matplotlib
Requires-Dist: scipy
Requires-Dist: cython
Requires-Dist: astropy
Requires-Dist: ccdproc
Requires-Dist: astroplan
